kindle_maker-1.0.4.data/purelib/kindle_maker/__init__.py
kindle_maker-1.0.4.data/purelib/kindle_maker/ebooklib.py
kindle_maker-1.0.4.data/purelib/kindle_maker/kindlegen.py
kindle_maker-1.0.4.data/purelib/kindle_maker/bin/linux/kindlegen
kindle_maker-1.0.4.data/purelib/kindle_maker/bin/mac/kindlegen
kindle_maker-1.0.4.data/purelib/kindle_maker/templates/cover.jpg
kindle_maker-1.0.4.data/purelib/kindle_maker/templates/opf.xml
kindle_maker-1.0.4.data/purelib/kindle_maker/templates/toc.html
kindle_maker-1.0.4.data/purelib/kindle_maker/templates/toc.xml
kindle_maker-1.0.4.dist-info/METADATA
kindle_maker-1.0.4.dist-info/WHEEL
kindle_maker-1.0.4.dist-info/entry_points.txt
kindle_maker-1.0.4.dist-info/top_level.txt
kindle_maker-1.0.4.dist-info/RECORD
